Services/__init__.py
Services/awshelper.py
Services/cloudwatch/CloudWatchlogs.py
Services/cloudwatch/CloudWatchlogsAnsible.py
Services/cloudwatch/__init__.py
Services/display/DisplayData.py
Services/display/__init__.py
awsassistant-1.2.1.dist-info/LICENCE
awsassistant-1.2.1.dist-info/METADATA
awsassistant-1.2.1.dist-info/WHEEL
awsassistant-1.2.1.dist-info/entry_points.txt
awsassistant-1.2.1.dist-info/top_level.txt
awsassistant-1.2.1.dist-info/RECORD
