Metadata-Version: 2.1
Name: awsassistant
Version: 1.2.1
Summary: Python command line application to help us with aws api
Home-page: UNKNOWN
Author: devesh bajaj
Author-email: deveshbajaj59@gmail.com
License: UNKNOWN
Platform: UNKNOWN
Requires-Dist: pytz
Requires-Dist: prettytable
Requires-Dist: colorama
Requires-Dist: boto3
